jTookkit/__init__.py
jTookkit/jConfig.py
jTookkit/jDateTime.py
jTookkit/jLogging.py
jTookkit/jSplunk.py
j_utilities_toolkit-0.0.2.dist-info/licenses/LICENSE
j_utilities_toolkit-0.0.2.dist-info/METADATA
j_utilities_toolkit-0.0.2.dist-info/WHEEL
j_utilities_toolkit-0.0.2.dist-info/top_level.txt
j_utilities_toolkit-0.0.2.dist-info/RECORD
