Metadata-Version: 2.4
Name: j-utilities-toolkit
Version: 0.0.2
Summary: A collection of reusable utilities including logging, configuration, timing, debugging, and more.
Author-email: Jay Curtis <jaysuzi5@gmail.com>
License: MIT
Project-URL: Homepage, https://github.com/jaysuzi5/jToolkit
Project-URL: Issues, https://github.com/jaysuzi5/jToolkit/issues
License-File: LICENSE
Requires-Dist: python-dotenv>=1.1.1
Requires-Dist: pytz>=2025.2
Requires-Dist: splunk-sdk>=2.1.1
Dynamic: license-file
